{
  "slug": "33195-2",
  "url": "https://financialedge.com.ng/33195-2/",
  "title": "United Steps Against Cancer: Access Holdings Rallies for Breast Cancer Awareness - FinancialEDGE",
  "description": "This past Saturday, more than 300 people, many of them employees of Access Holdings, came together to walk for a cause that touches every family, every community, and every heart. In recognition of Breast Cancer Awareness Month, the Group hosted a 6-kilometre walk to raise awareness, encourage early detection, and remind everyone that the",
  "featuredImage": "https://res.cloudinary.com/dw7w2at8k/image/upload/v1772448445/financialedge/img_20251029_wa0028.jpg",
  "publishedAt": "2025-10-29T07:47:39+01:00",
  "html": "<div class=\"entry-content wp-elements-c2ff229175929f05f608f3009aa73423 wp-block-post-content has-text-color has-dark-color is-layout-flow wp-block-post-content-is-layout-flow\"><p>This past Saturday, more than 300 people, many of them employees of Access Holdings, came together to walk for a cause that touches every family, every community, and every heart.</p>\n<p>&nbsp;</p>\n<p>In recognition of Breast Cancer Awareness Month, the Group hosted a 6-kilometre walk to raise awareness, encourage early detection, and remind everyone that the fight against breast cancer begins with information, compassion, and action. This was a statement that Access cares and stands with survivors.</p>\n<p>&nbsp;</p>\n<p>At the end of the morning, participants gathered for health talks and free breast cancer screenings practical steps that turned advocacy into impact.</p>\n<p>By the end of the day, about 50 women had been screened, several receiving guidance for follow-up care. Each test represented a story, a mother, sister, or friend choosing knowledge over fear.</p>\n<p>&nbsp;</p>\n<p><strong>Purpose in Every Step</strong></p>\n<p>&nbsp;</p>\n<p>For Access Holdings, initiatives like this are expressions of a larger purpose: to make positive impact across Africa.</p>\n<p>Health, alongside education, environment, and entrepreneurship, remains one of the Group’s core sustainability pillars, because a healthy society is the foundation on which progress is built.</p>\n<p>&nbsp;</p>\n<p>The walk was filled with laughter, shared stories, and moments of reflection, reminders that compassion is strongest when practiced together.</p>\n<p>Employees showed up, walking side by side with colleagues, friends, and families, proof that collective strength lies not only in our numbers, but in unity of purpose.</p>\n<p>&nbsp;</p>\n<p><strong>More Than an Event</strong></p>\n<p>&nbsp;</p>\n<p>The day was not about medals or finish lines. It was about movement with meaning, a demonstration that small actions, taken together, can ripple outward to touch countless lives.</p>\n<p>&nbsp;</p>\n<p>As October comes to an end Access Holdings remains committed to using its platform to spread awareness, promote early detection, and support those affected by breast cancer.</p>\n<p>&nbsp;</p>\n<p>&nbsp;</p>\n<p>&nbsp;</p>\n</div>",
  "section": "Health Matters",
  "sectionSlug": "health-matters"
}