{
  "slug": "another-set-of-50-winners-emerge-in-monthly-draw-of-ongoing-polaris-save-n-win-promo",
  "type": "post",
  "title": "Another Set of 50 Winners Emerge in monthly draw of ongoing Polaris &#8220;Save N Win&#8221; Promo",
  "description": "Another set of 50 lucky Nigerians have emerged winners in the monthly draw of ongoing Polaris &#8220;Save N Win&#8221; promo. The draw which took place at the Polaris Bank Headquarters in Victoria Isl",
  "publishedAt": "2023-10-13T08:03:31+01:00",
  "featuredImage": "https://financialedge.com.ng/wp-content/uploads/2020/07/Polaris-Bank-Logo.jpg",
  "sourceUrl": "https://financialedge.com.ng/another-set-of-50-winners-emerge-in-monthly-draw-of-ongoing-polaris-save-n-win-promo/",
  "section": "Money Market",
  "sectionSlug": "money-market",
  "html": "<p>Another set of 50 lucky Nigerians have emerged winners in the monthly draw of ongoing Polaris &#8220;Save N Win&#8221; promo.</p>\n<p>The draw which took place at the Polaris Bank Headquarters in Victoria Island, Lagos last weekend, is in line with the Bank&#8217;s commitment to rewarding its esteemed customers.</p>\n<p>The draw event was witnessed by representatives of the relevant regulatory Agencies in Nigeria who attested to the transparency of the draw.</p>\n<p>The representatives of Federal Competition &amp; Consumer Protection Commission (FCCPC) and Advertising Regulatory Council of Nigeria (ARCON) all confirmed that the 50 lucky winners were selected from various regions spanning the six geo-political zones of Nigeria with each winner receiving a cash prize of N10,000.</p>\n<p>During the draw, winners were called at random using a hybrid media technology which enabled in-premises event, as well as virtual participation of several customers and members of the public through the Bank’s virtual network and social media handles.</p>\n<p>The &#8220;Save N Win&#8221; promo has excited numerous customers of Polaris Bank across Nigeria, offering them a unique opportunity to save money and win cash prizes.</p>\n<p>This initiative not only promotes a culture of saving but also provides customers with a chance to achieve their financial goals while enjoying the thrill of winning.</p>\n<p>The 50 lucky individuals account with Polaris Bank automatically get credited in five (5) working days with their winning cash prizes.</p>\n<p>Speaking at the draw, Polaris Bank&#8217;s Chief Digital Officer (CDO), Dele Adeyinka, expressed the Bank&#8217;s gratitude to its customers for their unwavering trust and support.</p>\n<p>He emphasized the Bank&#8217;s commitment to improving the financial well-being of its current customers and prospects. He thanked them for choosing Polaris Bank as their preferred banking partner.</p>\n<p>Polaris Bank remains dedicated to providing innovative financial solutions and rewarding its customers for their loyalty.</p>\n<p>With the ongoing &#8220;Save N Win&#8221; promo, Polaris Bank continues to demonstrate its commitment to empowering individuals and communities through financial inclusion and responsible banking.</p>\n<p>Below are four (4) ways to participate in the ongoing Polaris Save &amp; Win promo:</p>\n<p>1. Download VULTe on iOS and the App store to open a Polaris Savings Account or dial USSD *833*0# on your phone or log into Polaris Bank savings portal.</p>\n<p>2. Grow your account by N10,000 or more and maintain for 30 days or by N10,000 for 3 consecutive months to qualify for monthly &amp; quarterly draws respectively.</p>\n<p>3. If your account is dormant, you can reactivate your account without visiting the Bank by simply dialing *833*30#.</p>\n<p>4. Follow the Bank’s handles @polarisbankltd across all social media platforms or visit the website to stay updated.</p>\n<p>Polaris Bank, adjudged Digital Bank of the Year 2021 and 2022, is a future-determining Bank committed to delivering industry-defining products for individuals and businesses.</p>\n<p>&nbsp;</p>\n"
}