{
  "slug": "cbn-says-other-african-countries-understudying-e-naira",
  "type": "post",
  "title": "CBN Says Other African Countries Understudying e-Naira",
  "description": "The Central Bank of Nigeria (CBN) has stated that the success and acceptance of the e-Naira has attracted other African countries to understudy the model and basics of the Central Bank Digital Currenc",
  "publishedAt": "2021-11-13T17:36:53+01:00",
  "featuredImage": null,
  "sourceUrl": "https://financialedge.com.ng/cbn-says-other-african-countries-understudying-e-naira/",
  "section": "Money Market",
  "sectionSlug": "money-market",
  "html": "<p>The Central Bank of Nigeria (CBN) has stated that the success and acceptance of the e-Naira has attracted other African countries to understudy the model and basics of the Central Bank Digital Currency (CBDC).</p>\n<p>Speaking on the sidelines of the CBN special day at the ongoing Lagos International Trade Fair yesterday, Director, Corporate Communications of the apex bank, Osita Nwanisobi, noted that as one of the first countries in the world to have adopted the digital currency, Nigeria has become a role model to many other central banks in Africa and beyond.</p>\n<p>He said, “Presently, many African countries are in the country trying to understand and see how they can also start their own digital currency.</p>\n<p>Many central banks across the world are still trying to understand it and the CBN has made history as one of the first to achieve this. The world is moving away from fossil fuel and we are entering a digital world. If we do not join the train now, we would be left behind.”</p>\n<p>&nbsp;</p>\n"
}