{
  "slug": "dbn-set-for-structured-entrepreneurship-training-funding-of-msmes",
  "type": "post",
  "title": "DBN set for Structured Entrepreneurship Training, Funding of MSMEs",
  "description": "The Development Bank of Nigeria (DBN) says it has completed all arrangements to boost the Micro, Small, and Medium Enterprises (MSMEs) through a Capacity building exercise, which is one ofits core man",
  "publishedAt": "2022-08-15T11:21:25+01:00",
  "featuredImage": "https://res.cloudinary.com/dw7w2at8k/image/upload/v1772449121/financialedge/dbn_md_tony_okpanachi.jpg",
  "sourceUrl": "https://financialedge.com.ng/dbn-set-for-structured-entrepreneurship-training-funding-of-msmes/",
  "section": "Money Market",
  "sectionSlug": "money-market",
  "html": "<p>The Development Bank of Nigeria (DBN) says it has completed all arrangements to boost the Micro, Small, and Medium Enterprises (MSMEs) through a Capacity building exercise, which is one ofits core mandates, as well as providing access to finance to MSMEs and partial credit guarantee to the participating financial institution on a market conforming basis to enable them to lend to small businesses.</p>\n<p>Specifically, the development finance institution said it is committed to building the capacity of the Nigerian MSMEs to enable them to formalize, grow and become more bankable to get easy access to available credit. Commenting on the initiative, the DBN Managing Director/CEO Dr. Tony Okpanachi said part of DBN&#8217;s role is to partner with financial institutions and collaborate with them to provide financing facilities to MSMEs.</p>\n<p>In many cases, DBN also offers technical assistance programs to these institutions to augment their capacity to lend to MSMEs. According to Okpanachi, &#8220;In the short term, we plan to strengthen our catalytic role in the Nigerian economy by expanding our reach to more MSMEs in underserved regions such as crisis-impacted areas and enhancing development impact in other key areas such as women- and youth-owned enterprises, startups, and first-time borrowers.</p>\n<p>&#8220;We will continue to provide capacity building for MSMEs and technical assistance to our participating financial institutions to strengthen their lending capacity to MSMEs.&#8221;In the medium term, we plan to complete the digital transformation efforts currently underway within the Bank and expand our channels of disbursement to MSMEs, which speaks to our drive for increased collaboration with other players within the space.</p>\n<p>&#8220;In the long term, our focus is for DBN to be recognized locally and internationally as the foremost institution driving the growth and sustainability of the Nigerian economy through the provision of financing support to MSMEs.&#8221;</p>\n<p>Whilst explaining the structured Entrepreneurship Training to the executive members of the Finance Correspondents Association of Nigeria (FICAN) who paid a courtesy visit to the  Bank&#8217;s Lagos office, the Head, Corporate Services DBN, Idris Salihu said the Bank would be deploying the DBN Learning Management System (LMS)- a free learning portal with carefully curated self-paced courses.</p>\n<p>The portal is open to all Nigerian MSMEs who are interested in acquiring the right knowledge needed to succeed in doing business in Nigeria. In addition, Salihu stated, that DBN will be selecting the best 200 businesses to attend face-to-face training in Lagos and Abuja.</p>\n<p>This physical session would be an opportunity for businesses to practically apply important principles to their various businesses, discuss; and receive business support in specific areas of need, he stressed. He further explained that all businesses will be eligible to apply for the capacity-building programme.</p>\n<p>&#8220;All applications must be submitted online through the application portal. Interested businesses must register on the DBN BizAid application and must complete a minimum of 4 mandatory courses on the DBN BizAid Learning Management Platform and obtain an average score of 70 percent,&#8221; Salihu said. The courses that must be completed according to the DBN spokesperson are Accounting &amp; Bookkeeping, Sustainability for MSMEs, Marketing and Sales, Techniques as well as Credit Management/Access to Finance.</p>\n<p>In an earlier statement, DBN noted that all businesses who have completed the 4 courses by September 23rd will receive an email with a link to apply for the face-to-face training. Upon submission of the application form, an email confirming receipt will be sent to the applicant within 24 hours.</p>\n<p>Applicants will be screened and shortlisted from the close of the application based on the eligibility criteria. Selection will be carried out using the defined selection criteria from the pool of shortlisted applications and communication with successful applicants shall be by email to the email address provided and a phone call to the phone number provided on the application form.</p>\n<p>On eligibility criteria, the Bank specified that the owner of a business must be a citizen or legal resident of Nigeria of 18 years and above.</p>\n<p>Also, the business must be based in Nigeria and must be for-profit from any sector, even as applicants must be available to commit to the training schedule once accepted. It further stated that Bankability- Level, and readiness to upscale their businesses are important criteria for selection.</p>\n<p>Others are Feasibility and Sustainability of the business model; Scalability or demonstrated potential for growth of the business to create jobs. DBN is a wholly wholesale development finance institution. Its key activity which is providing finance to MSMEs is carried out through financial intermediaries which it refers to as Participating Financial Intermediaries (PFIs).</p>\n<p>The PFIs become the face of DBN since the Bank cannot interface directly with the end-borrowers. This, to a great extent, limits the level of knowledge even the end-borrowers have about the institution. However, there is a commitment from the Bank to continue to accelerate its awareness campaign and stakeholder engagements to drive access to finance by the MSMEs and also, to deliver the much-needed developmental impact across sectors.</p>\n"
}