{
  "slug": "embracing-artificial-intelligence-for-pr-efficiency",
  "type": "post",
  "title": "Embracing Artificial Intelligence For PR Efficiency",
  "description": "Embracing Artificial Intelligence for PR efficiency at the 8th edition of the Lagos Digital PR Summit, with theme: “Reinventing Public Relations Proficiencies With Artificial Intelligence”, organized ",
  "publishedAt": "2023-10-20T07:22:44+01:00",
  "featuredImage": "https://financialedge.com.ng/wp-content/uploads/2023/10/PR-TEN.jpg",
  "sourceUrl": "https://financialedge.com.ng/embracing-artificial-intelligence-for-pr-efficiency/",
  "section": "Gallery",
  "sectionSlug": "gallery",
  "html": "<p>Embracing Artificial Intelligence for PR efficiency at the 8<sup>th</sup> edition of the Lagos Digital PR Summit, with theme: “Reinventing Public Relations Proficiencies With Artificial Intelligence”, organized by the Nigerian Institute of Public Relations (NIPR), Lagos state chapter.</p>\n"
}