{
  "slug": "fidelity-bank-brings-relief-to-rivers-state-community-with-food-bank-initiative",
  "type": "post",
  "title": "Fidelity Bank Brings Relief to Rivers State Community with Food Bank Initiative",
  "description": "In a strong demonstration of its commitment to community development and poverty alleviation, leading financial institution, Fidelity Bank Plc has donated food packs to over 1,500 individuals in Ihie ",
  "publishedAt": "2025-06-08T06:24:25+01:00",
  "featuredImage": "https://res.cloudinary.com/dw7w2at8k/image/upload/v1772449446/financialedge/img_20250605_wa0020.jpg",
  "sourceUrl": "https://financialedge.com.ng/fidelity-bank-brings-relief-to-rivers-state-community-with-food-bank-initiative/",
  "section": "Money Market",
  "sectionSlug": "money-market",
  "html": "<p>In a strong demonstration of its commitment to community development and poverty alleviation, leading financial institution, Fidelity Bank Plc has donated food packs to over 1,500 individuals in Ihie Town, Etche Local Government Area of Rivers State, through its Food Bank initiative.</p>\n<p>Speaking at the donation event, the Regional Bank Head, Rivers/Bayelsa 1 &amp; South Commercial, Fidelity Bank Plc, Mr. Ibisiki Eretoru, noted that the success of the bank is essentially linked to the well-being and prosperity of the communities in which it operates.</p>\n<p>“The Food Bank Initiative is our way of contributing to the well-being of our host communities through regular food support. Each month, with the support of our network of dedicated partners, we distribute food packs to individuals and families across the country,” Eretoru said.</p>\n<p>He further highlighted that the Fidelity Food Bank initiative, launched in April 2023, is part of the bank’s broader corporate social responsibility drive aimed at combating hunger and improving livelihoods across Nigeria. The initiative also perfectly aligns with the United Nations’ Sustainable Development Goal 2 which aims to achieve zero hunger.</p>\n<p>“To date, we have distributed over 200,000 food packs through similar outreaches aimed at supporting individuals, strengthening businesses and transforming entire economies,” Eretoru added.</p>\n<p>The food distribution in Ihie town was executed in partnership with The Reach Nigeria Foundation, a non-profit organization focused on sustainable development. Speaking at the outreach, the Foundation’s CEO, Benedicta Ibiyemie Ayarete, said that the community was selected due to its need for food support during the post-planting and pre-harvest period.</p>\n<p>“Though Ihie is an agrarian community, we identified it as needing food support at this time. The peaceful nature of the community also makes it a viable location for Fidelity Bank to sustain and grow its presence. We are proud to be part of the meaningful impact of this outreach on the people,” she explained.</p>\n<p>Expressing his gratitude, the paramount ruler of Ihie community, His Royal Highness, Eze Richard Amadi, commended the bank’s timely intervention, describing it as “a stitch in time” and a noteworthy effort that addresses the needs of the people.</p>\n<p>Also speaking at the event, Chairman of the Ihie Community Development Committee, Mr. Stephen Asoh, expressed appreciation to Fidelity Bank, highlighting the positive difference the donations will make in the lives of many residents.</p>\n<p>One of the beneficiaries, Mike Okere, praised Fidelity Bank for the initiative and called on other financial institutions to emulate the bank’s approach to community engagement and impact.</p>\n<p>The Fidelity Food Bank continues to be a beacon of hope for underserved communities across Nigeria, reflecting the bank’s unwavering commitment to social responsibility and inclusive growth.</p>\n<p>Ranked among the best banks in Nigeria, Fidelity Bank Plc is a full-fledged Commercial Deposit Money Bank serving over 9.1 million customers through digital banking channels, its 255 business offices in Nigeria and United Kingdom subsidiary, FidBank UK Limited.</p>\n<p>The Bank is a recipient of multiple local and international Awards, including the 2024 Excellence in Digital Transformation &amp; MSME Banking Award by BusinessDay Banks and Financial Institutions (BAFI) Awards; the 2024 Most Innovative Mobile Banking Application award for its Fidelity Mobile App by Global Business Outlook, and the 2024 Most Innovative Investment Banking Service Provider award by Global Brands Magazine.</p>\n<p>Additionally, the Bank was recognized as the Best Bank for SMEs in Nigeria by the Euromoney Awards for Excellence and as the Export Financing Bank of the Year by the BusinessDay Banks and Financial Institutions (BAFI) Awards.</p>\n<p>&nbsp;</p>\n<p><em><strong>Photo caption; L-R: The Branch Leader, Trans-Amadi 1 Port Harcourt, Bob Anyanwu Representing the Regional Bank Head Rivers and Bayelsa 1 &amp; South Commercial, Ibisiki Eretoru; one of the beneficiaries of the Food Bank Donation, Ogechi Friday; The Clan Head, Ozuzu Etche, HRH Eze Josiah Nwagwu; the Team Lead, CSR, Fidelity Bank Plc, Victoria Abuka; and the CEO, Reach Nigeria Foundation, Benedicta Ebi; during the Fidelity Food Bank Distribution in Ihie Community, Etche Local Government Area of Rivers State.</strong></em></p>\n"
}