{
  "slug": "nimasa-delegation-set-for-philippines-over-cadets-protest-at-nigerian-embassy",
  "type": "post",
  "title": "NIMASA Delegation Set For Philippines Over Cadets Protest At Nigerian Embassy",
  "description": "Following the protest by NIMASA NDSP 2013 cadets at the Nigerian Embassy in the Philippines, the management of NIMASA is sending a delegation for an assessment visit this October. “We wish to let the ",
  "publishedAt": "2022-10-08T17:31:06+01:00",
  "featuredImage": "https://res.cloudinary.com/dw7w2at8k/image/upload/v1772448272/financialedge/dr_dayo_mobereola_nimasa_dg.jpg",
  "sourceUrl": "https://financialedge.com.ng/nimasa-delegation-set-for-philippines-over-cadets-protest-at-nigerian-embassy/",
  "section": "News",
  "sectionSlug": "news",
  "html": "<p>Following the protest by NIMASA NDSP 2013 cadets at the Nigerian Embassy in the Philippines, the management of NIMASA is sending a delegation for an assessment visit this October.</p>\n<p>“We wish to let the public know that we are monitoring the unfortunate development in the Philippines involving NIMASA NSDP 2013 cadets, as seen in a recent online video. And to assure Nigerians that NIMASA has received Ministerial approval for an assessment visit this October to ascertain, first-hand, the issues to fully and finally address them”.</p>\n<p>“Our Executive Director, Maritime Labour and Cabotage Services, Engr. Victor Ochei, will lead the fact-finding mission to the Philippines to engage with the school and the cadets. As responsible management, we must deal with this from an informed position, as the matter far predates this administration”.</p>\n<p>“While we regret the embarrassment this may have caused all concerned; we urge caution and avoidance of any speculative reporting until the official outcome of the on-the-spot evaluation to the Philippines is submitted”.</p>\n"
}