{
  "slug": "sec-warns-on-proliferation-of-unregistered-online-platforms",
  "type": "post",
  "title": "SEC warns on proliferation of Unregistered Online Platforms",
  "description": "The Securities and Exchange Commission has warned the investing public on the proliferation of unregistered online investment and trading platforms facilitating access to trading in securities listed ",
  "publishedAt": "2021-04-08T19:31:47+01:00",
  "featuredImage": "https://res.cloudinary.com/dw7w2at8k/image/upload/v1772449011/financialedge/image0_1_aHR0cHM6.jpg",
  "sourceUrl": "https://financialedge.com.ng/sec-warns-on-proliferation-of-unregistered-online-platforms/",
  "section": "Capital Market",
  "sectionSlug": "capital-market",
  "html": "<p>The Securities and Exchange Commission has warned the investing public on the proliferation of unregistered online investment and trading platforms facilitating access to trading in securities listed in foreign markets.</p>\n<p>This was contained in a circular to Capital Market Operators issued by the Management of the Commission in Abuja, on Thursday, April 8, 2021.</p>\n<p>According to the Circular, “The attention of the SEC has been drawn to the existence of several providers of online investment and trading platforms which purportedly facilitate direct access of the investing public in the Federal Republic of Nigeria to securities of foreign Companies listed on Securities Exchanges registered in other jurisdictions.</p>\n<p>“These platforms also claim to be operating in partnership with Capital Market operators (CMOs) registered with the Commission”.</p>\n<p>The Commission categorically stated further that by the provisions of Sections 67-70 of the Investments and Securities Act (ISA), 2007 and Rules 414 &amp; 415 of the SEC Rules and Regulations, only foreign securities listed on any Exchange registered in Nigeria may be issued, sold or offered for sale or subscription to the Nigerian public.</p>\n<p>Accordingly, the SEC notified CMOs who work in concert with the referenced online platforms of the Commission’s position and advised them to desist henceforth.</p>\n<p>“The Commission enjoins the investing public to seek clarification as may be required via its established channels of communication on investment products advertised through conventional or online mediums” the statement added.</p>\n"
}