{
  "slug": "senate-lauds-nnpc-on-gas-projects-financial-audit-report",
  "type": "post",
  "title": "Senate Lauds NNPC on Gas Projects, Financial Audit Report",
  "description": "The Senate Committee on Gas has commended the Nigerian National Petroleum Corporation (NNPC) on the various gas development projects it has undertaken, especially the Ajaokuta- Kaduna- Kano (AKK) gas ",
  "publishedAt": "2020-11-21T03:42:26+01:00",
  "featuredImage": null,
  "sourceUrl": "https://financialedge.com.ng/senate-lauds-nnpc-on-gas-projects-financial-audit-report/",
  "section": "Energy",
  "sectionSlug": "energy",
  "html": "<p>The Senate Committee on Gas has commended the <strong>Nigerian National Petroleum Corporation (NNPC)</strong> on the various gas development projects it has undertaken, especially the <strong>Ajaokuta- Kaduna- Kano (AKK) gas pipeline project</strong>.</p>\n<p>Speaking during the 2021 Budget Defense and Performance Appraisal meeting with officials of the Corporation which held at the National Assembly Complex, <strong>Chairman of the Committee, Senator James Manager,</strong> expressed satisfaction with the various gas development projects embarked upon by the NNPC despite the impact of Covid-19 on the oil and gas industry, saying: “We are proud of the AKK and some of your other projects”.</p>\n<p>He said the interface between the committee and the NNPC would have been more frequent but for the lockdown due to the Covid-19 pandemic. He seized the opportunity to reassure the Corporation that his committee would undertake an oversight visit to the projects for proper assessment soon.</p>\n<p>On his part, a member of the Committee, who is also the immediate past Chairman of the Committee, Senator Albert Akpan Bassey, said NNPC under the leadership of Mallam Mele Kyari has taken the Corporation to a new height by publishing the 2018 and 2019 Audited Financial Statements and for reducing losses by over 95 per cent.</p>\n<p>“I want to commend the team led by the present GMD, a team of dedicated and passionate Nigerians. If they can reduce losses drastically within such a short time, I am sure the next report will reveal huge profit to the country. We must give them our support and cooperation,” he stated.</p>\n<p>Speaking earlier during a presentation, the <strong>Group Managing Director of the NNPC, Mallam Mele Kyari,</strong> who was represented by the Chief Operating Officer, Gas and Power, Engr. Yusuf Usman, attributed the success of the Corporation in the gas sector to the support and cooperation of the Committee and the entire legislature.</p>\n<p>He said gas supply to power has improved significantly, which was evident in the improved power supply currently being witnessed in the country. “We have significant gas in the network currently, but the challenge however, is transmission,” the COO stated.</p>\n<p>On the AKK pipeline project, Engr. Usman told the lawmakers that it was designed to supply 2billion cubic feet of gas per day (2bcfd), stressing that it would be the primary source of gas for the power plants currently being developed in Abuja, Kaduna and Kano.</p>\n<p>&nbsp;</p>\n"
}